{
    "date": "2023.01.25",
    "title": "【2023/01/25 17:00掲載】電子カルテサーバの障害について",
    "contents": "<p>本日、日本時間2023年1月25日の16:30頃に発生したデータセンター（Microsoft Azureサービス）の障害により、</p><p>現在電子カルテの操作が不安定となっております。</p><br /><p>弊社サポートから順番にご案内の電話を入れさせていただいておりますが、</p><p>電子カルテが動作しない場合は「電子カルテ（オフラインカルテ）」のご利用に切換えいただきますようお願い申し上げます。</p><br /><p>ご迷惑をお掛けして大変申し訳ございません。</p><p>ご不明な点がございましたらページ最下部の「お問い合わせ先」までお問い合わせください。</p>",
    "tag": [
        {
            "name": "障害連絡",
            "fontColor": "#FFFFFF",
            "bgColor": "#FF3333"
        }
    ]
}